Workbook

Sheet Synthese KPI
A1: SYNTHESE ET INDICATEURS CLES
A2: Reflete desormais le scenario RACHAT PHASE (existant + tranches autofinancees). Le detail construction neuve reste dans les onglets Hypotheses/CAPEX/Compte de resultat/Financement, a titre de comparaison.
A4: INDICATEURS D'EXPLOITATION
C5: Annee 1 | D5: Annee 2 | E5: Annee 3 | F5: Annee 4 | G5: Annee 5 | H5: Annee 6 | I5: Annee 7
B6: Taux d'occupation | C6: =Hypotheses!C11 -> 0.35 | D6: =Hypotheses!D11 -> 0.45 | E6: =Hypotheses!E11 -> 0.55 | F6: =Hypotheses!F11 -> 0.6 | G6: =Hypotheses!G11 -> 0.65 | H6: =Hypotheses!H11 -> 0.65 | I6: =Hypotheses!I11 -> 0.65
B7: ADR - prix moyen chambre (EUR) | C7: =Hypotheses!C10 -> 190 | D7: =Hypotheses!D10 -> 200 | E7: =Hypotheses!E10 -> 210 | F7: =Hypotheses!F10 -> 216 | G7: =Hypotheses!G10 -> 223 | H7: =Hypotheses!H10 -> 229 | I7: =Hypotheses!I10 -> 236
B8: RevPAR (revenu par chambre disponible) | C8: ='Scenario Rachat'!C40/('Scenario Rachat'!C33*Hypotheses!$C$6) -> 66.5 | D8: ='Scenario Rachat'!D40/('Scenario Rachat'!D33*Hypotheses!$C$6) -> 90 | E8: ='Scenario Rachat'!E40/('Scenario Rachat'!E33*Hypotheses!$C$6) -> 115.5 | F8: ='Scenario Rachat'!F40/('Scenario Rachat'!F33*Hypotheses!$C$6) -> 129.6 | G8: ='Scenario Rachat'!G40/('Scenario Rachat'!G33*Hypotheses!$C$6) -> 144.95 | H8: ='Scenario Rachat'!H40/('Scenario Rachat'!H33*Hypotheses!$C$6) -> 148.85 | I8: ='Scenario Rachat'!I40/('Scenario Rachat'!I33*Hypotheses!$C$6) -> 153.4
A10: INDICATEURS FINANCIERS
C11: Annee 1 | D11: Annee 2 | E11: Annee 3 | F11: Annee 4 | G11: Annee 5 | H11: Annee 6 | I11: Annee 7
B12: Chiffre d'affaires total | C12: ='Scenario Rachat'!C42 -> 149518.6 | D12: ='Scenario Rachat'!D42 -> 202356 | E12: ='Scenario Rachat'!E42 -> 454457.85 | F12: ='Scenario Rachat'!F42 -> 509937.12 | G12: ='Scenario Rachat'!G42 -> 814763.95 | H12: ='Scenario Rachat'!H42 -> 836685.85 | I12: ='Scenario Rachat'!I42 -> 1034713.7
B13: EBITDA | C13: ='Scenario Rachat'!C52 -> 60144.322 | D13: ='Scenario Rachat'!D52 -> 92749.428 | E13: ='Scenario Rachat'!E52 -> 241344.72 | F13: ='Scenario Rachat'!F52 -> 275104.4 | G13: ='Scenario Rachat'!G52 -> 447914.56 | H13: ='Scenario Rachat'!H52 -> 459348 | I13: ='Scenario Rachat'!I52 -> 570071.77
B14: Marge EBITDA | C14: =C13/C12 -> 0.40225311 | D14: =D13/D12 -> 0.4583478 | E14: =E13/E12 -> 0.53106073 | F14: =F13/F12 -> 0.53948692 | G14: =G13/G12 -> 0.54974764 | H14: =H13/H12 -> 0.54900893 | I14: =I13/I12 -> 0.5509464
B15: Resultat net | C15: ='Scenario Rachat'!C67 -> 3900.4672 | D15: ='Scenario Rachat'!D67 -> 13151.531 | E15: ='Scenario Rachat'!E67 -> 107139.07 | F15: ='Scenario Rachat'!F67 -> 120182.53 | G15: ='Scenario Rachat'!G67 -> 236428.84 | H15: ='Scenario Rachat'!H67 -> 240646.88 | I15: ='Scenario Rachat'!I67 -> 324258.32
A17: STRUCTURE DE FINANCEMENT
B18: CAPEX total | C18: ='Scenario Rachat'!C21 -> 1047274.7
B19: Fonds propres investis | C19: ='Scenario Rachat'!C28 -> 680728.53
B20: Emprunt bancaire | C20: ='Scenario Rachat'!C29 -> 366546.13
B21: Cash-flow cumule fin Annee 7 (investissement total, avant valeur terminale) | C21: ='Scenario Rachat'!I93 -> -680057.36
B25: Annee | C25: 1 | D25: 2 | E25: 3 | F25: 4 | G25: 5 | H25: 6 | I25: 7
B26: CA total (k EUR) | C26: =C12/1000 -> 149.5186 | D26: =D12/1000 -> 202.356 | E26: =E12/1000 -> 454.45785 | F26: =F12/1000 -> 509.93712 | G26: =G12/1000 -> 814.76395 | H26: =H12/1000 -> 836.68585 | I26: =I12/1000 -> 1034.7137
B27: EBITDA (k EUR) | C27: =C13/1000 -> 60.144322 | D27: =D13/1000 -> 92.749428 | E27: =E13/1000 -> 241.34472 | F27: =F13/1000 -> 275.1044 | G27: =G13/1000 -> 447.91456 | H27: =H13/1000 -> 459.348 | I27: =I13/1000 -> 570.07177

Sheet Scenario Rachat
A1: SCENARIO RACHAT PHASE — CROISSANCE AUTOFINANCEE, DETTE MINIMISEE
A2: Tranches reduites + financement dedie par tranche (dette limitee, remboursee sur le cash-flow qu'elle genere). Base : Vohilava, 480 000 EUR, 4 villas.
A4: 1. ACQUISITION ET RENOVATION (Annee 0)
B5: Prix d'acquisition (murs + terrain + fonds de commerce) | C5: 480000
B6: Frais d'acquisition (notaire, due diligence, EDBM, audit) | C6: 0.08
B7: Renovation haut de gamme + autonomie - villas existantes (par unite) | C7: 45000
B8: Renovation espaces communs (restaurant, reception, piscine) | C8: 90000
B9: Etudes, permis, repositionnement de marque, marketing de relance | C9: 65000
A11: 2. PLAN DE PHASAGE — TRANCHES REDUITES POUR RESTER AUTOFINANCABLES
B12: Tranche | C12: Chambres | D12: Annee mise en service | E12: Construction (EUR) | F12: FF&E (EUR) | G12: Autonomie increm. (EUR) | H12: Total tranche (EUR)
B13: Tranche 0 - villas existantes renovees | C13: 4 | D13: 1 | E13: 0 | F13: 0 | G13: =CAPEX!$C$26*C13/Hypotheses!$C$5 -> 81666.667 | H13: =SUM(E13:G13) -> 81666.667
B14: Tranche 1 - construction (petite extension) | C14: 3 | D14: 3 | E14: =CAPEX!$C$14*C14 -> 450000 | F14: =CAPEX!$C$29*C14 -> 36000 | G14: =CAPEX!$C$26*C14/Hypotheses!$C$5 -> 61250 | H14: =SUM(E14:G14) -> 547250
B15: Tranche 2 - construction (petite extension) | C15: 3 | D15: 5 | E15: =CAPEX!$C$14*C15 -> 450000 | F15: =CAPEX!$C$29*C15 -> 36000 | G15: =CAPEX!$C$26*C15/Hypotheses!$C$5 -> 61250 | H15: =SUM(E15:G15) -> 547250
B16: Tranche 3 - construction (petite extension) | C16: 2 | D16: 7 | E16: =CAPEX!$C$14*C16 -> 300000 | F16: =CAPEX!$C$29*C16 -> 24000 | G16: =CAPEX!$C$26*C16/Hypotheses!$C$5 -> 40833.333 | H16: =SUM(E16:G16) -> 364833.33
B17: Total chambres a terme (doit = cible Hypotheses) | C17: =C13+C14+C15+C16 -> 12
B19: SOUS-TOTAL ACQUISITION + RENOVATION (Annee 0) | C19: =C5*(1+C6)+C7*C13+C8+C9+H13 -> 935066.67
B20: Imprevus / contingence (12%) | C20: =C19*0.12 -> 112208
B21: TOTAL INVESTISSEMENT INITIAL (Annee 0) | C21: =C19+C20 -> 1047274.7
A23: 3. FINANCEMENT PHASE 0 (emprunt reduit) ET FINANCEMENT DEDIE PAR TRANCHE
B24: Part fonds propres - Phase 0 (reduit l'emprunt initial) | C24: 0.65
B25: Part dette dediee par tranche de construction (le solde vient du cash-flow) | C25: 0.4 | D25: Dette plus faible que Phase 0 : chaque tranche est deja partiellement payee cash
B26: Duree du pret dedie par tranche (annees) | C26: 5
B28: Fonds propres investis - Annee 0 | C28: =C21*C24 -> 680728.53
B29: Emprunt bancaire principal - Annee 0 | C29: =C21*(1-C24) -> 366546.13
A31: 4. CHAMBRES DISPONIBLES ET CAPEX PAR ANNEE
C32: Annee 1 | D32: Annee 2 | E32: Annee 3 | F32: Annee 4 | G32: Annee 5 | H32: Annee 6 | I32: Annee 7
B33: Chambres disponibles | C33: =C13+IF(1>=$D$14,C14,0)+IF(1>=$D$15,C15,0)+IF(1>=$D$16,C16,0) -> 4 | D33: =C13+IF(2>=$D$14,C14,0)+IF(2>=$D$15,C15,0)+IF(2>=$D$16,C16,0) -> 4 | E33: =C13+IF(3>=$D$14,C14,0)+IF(3>=$D$15,C15,0)+IF(3>=$D$16,C16,0) -> 7 | F33: =C13+IF(4>=$D$14,C14,0)+IF(4>=$D$15,C15,0)+IF(4>=$D$16,C16,0) -> 7 | G33: =C13+IF(5>=$D$14,C14,0)+IF(5>=$D$15,C15,0)+IF(5>=$D$16,C16,0) -> 10 | H33: =C13+IF(6>=$D$14,C14,0)+IF(6>=$D$15,C15,0)+IF(6>=$D$16,C16,0) -> 10 | I33: =C13+IF(7>=$D$14,C14,0)+IF(7>=$D$15,C15,0)+IF(7>=$D$16,C16,0) -> 12
B34: CAPEX total de la tranche construite dans l'annee | C34: =IF(1=$D$14-1,$H$14,0)+IF(1=$D$15-1,$H$15,0)+IF(1=$D$16-1,$H$16,0) -> 0 | D34: =IF(2=$D$14-1,$H$14,0)+IF(2=$D$15-1,$H$15,0)+IF(2=$D$16-1,$H$16,0) -> 547250 | E34: =IF(3=$D$14-1,$H$14,0)+IF(3=$D$15-1,$H$15,0)+IF(3=$D$16-1,$H$16,0) -> 0 | F34: =IF(4=$D$14-1,$H$14,0)+IF(4=$D$15-1,$H$15,0)+IF(4=$D$16-1,$H$16,0) -> 547250 | G34: =IF(5=$D$14-1,$H$14,0)+IF(5=$D$15-1,$H$15,0)+IF(5=$D$16-1,$H$16,0) -> 0 | H34: =IF(6=$D$14-1,$H$14,0)+IF(6=$D$15-1,$H$15,0)+IF(6=$D$16-1,$H$16,0) -> 364833.33 | I34: =IF(7=$D$14-1,$H$14,0)+IF(7=$D$15-1,$H$15,0)+IF(7=$D$16-1,$H$16,0) -> 0
B35: dont finance par dette dediee | C35: =C34*$C$25 -> 0 | D35: =D34*$C$25 -> 218900 | E35: =E34*$C$25 -> 0 | F35: =F34*$C$25 -> 218900 | G35: =G34*$C$25 -> 0 | H35: =H34*$C$25 -> 145933.33 | I35: =I34*$C$25 -> 0
B36: dont autofinance (cash-flow / fonds propres) | C36: =C34-C35 -> 0 | D36: =D34-D35 -> 328350 | E36: =E34-E35 -> 0 | F36: =F34-F35 -> 328350 | G36: =G34-G35 -> 0 | H36: =H34-H35 -> 218900 | I36: =I34-I35 -> 0
A38: 5. COMPTE DE RESULTAT PHASE
C39: Annee 1 | D39: Annee 2 | E39: Annee 3 | F39: Annee 4 | G39: Annee 5 | H39: Annee 6 | I39: Annee 7
B40: CA Hebergement | C40: =C33*Hypotheses!$C$6*Hypotheses!C11*Hypotheses!C10 -> 97090 | D40: =D33*Hypotheses!$C$6*Hypotheses!D11*Hypotheses!D10 -> 131400 | E40: =E33*Hypotheses!$C$6*Hypotheses!E11*Hypotheses!E10 -> 295102.5 | F40: =F33*Hypotheses!$C$6*Hypotheses!F11*Hypotheses!F10 -> 331128 | G40: =G33*Hypotheses!$C$6*Hypotheses!G11*Hypotheses!G10 -> 529067.5 | H40: =H33*Hypotheses!$C$6*Hypotheses!H11*Hypotheses!H10 -> 543302.5 | I40: =I33*Hypotheses!$C$6*Hypotheses!I11*Hypotheses!I10 -> 671892
B41: CA Restauration + Spa/activites | C41: =C40*(Hypotheses!$C$14+Hypotheses!$C$15) -> 52428.6 | D41: =D40*(Hypotheses!$C$14+Hypotheses!$C$15) -> 70956 | E41: =E40*(Hypotheses!$C$14+Hypotheses!$C$15) -> 159355.35 | F41: =F40*(Hypotheses!$C$14+Hypotheses!$C$15) -> 178809.12 | G41: =G40*(Hypotheses!$C$14+Hypotheses!$C$15) -> 285696.45 | H41: =H40*(Hypotheses!$C$14+Hypotheses!$C$15) -> 293383.35 | I41: =I40*(Hypotheses!$C$14+Hypotheses!$C$15) -> 362821.68
B42: CA TOTAL | C42: =C40+C41 -> 149518.6 | D42: =D40+D41 -> 202356 | E42: =E40+E41 -> 454457.85 | F42: =F40+F41 -> 509937.12 | G42: =G40+G41 -> 814763.95 | H42: =H40+H41 -> 836685.85 | I42: =I40+I41 -> 1034713.7
B43: Commissions distribution | C43: =-C42*Hypotheses!$C$18 -> -17942.232 | D43: =-D42*Hypotheses!$C$18 -> -24282.72 | E43: =-E42*Hypotheses!$C$18 -> -54534.942 | F43: =-F42*Hypotheses!$C$18 -> -61192.454 | G43: =-G42*Hypotheses!$C$18 -> -97771.674 | H43: =-H42*Hypotheses!$C$18 -> -100402.3 | I43: =-I42*Hypotheses!$C$18 -> -124165.64
B44: CA NET | C44: =C42+C43 -> 131576.37 | D44: =D42+D43 -> 178073.28 | E44: =E42+E43 -> 399922.91 | F44: =F42+F43 -> 448744.67 | G44: =G42+G43 -> 716992.28 | H44: =H42+H43 -> 736283.55 | I44: =I42+I43 -> 910548.04
B46: Cout matieres restauration | C46: =-C41*Hypotheses!$C$19*0.6 -> -10066.291 | D46: =-D41*Hypotheses!$C$19*0.6 -> -13623.552 | E46: =-E41*Hypotheses!$C$19*0.6 -> -30596.227 | F46: =-F41*Hypotheses!$C$19*0.6 -> -34331.351 | G46: =-G41*Hypotheses!$C$19*0.6 -> -54853.718 | H46: =-H41*Hypotheses!$C$19*0.6 -> -56329.603 | I46: =-I41*Hypotheses!$C$19*0.6 -> -69661.763
B47: Masse salariale (ETP proportionnel aux chambres, plancher 8) | C47: =-MAX(ROUND(Hypotheses!$C$22*C33/Hypotheses!$C$5,0),8)*Hypotheses!$C$23*(1+Hypotheses!$C$24)^0 -> -27200 | D47: =-MAX(ROUND(Hypotheses!$C$22*D33/Hypotheses!$C$5,0),8)*Hypotheses!$C$23*(1+Hypotheses!$C$24)^1 -> -28288 | E47: =-MAX(ROUND(Hypotheses!$C$22*E33/Hypotheses!$C$5,0),8)*Hypotheses!$C$23*(1+Hypotheses!$C$24)^2 -> -40451.84 | F47: =-MAX(ROUND(Hypotheses!$C$22*F33/Hypotheses!$C$5,0),8)*Hypotheses!$C$23*(1+Hypotheses!$C$24)^3 -> -42069.914 | G47: =-MAX(ROUND(Hypotheses!$C$22*G33/Hypotheses!$C$5,0),8)*Hypotheses!$C$23*(1+Hypotheses!$C$24)^4 -> -63640.306 | H47: =-MAX(ROUND(Hypotheses!$C$22*H33/Hypotheses!$C$5,0),8)*Hypotheses!$C$23*(1+Hypotheses!$C$24)^5 -> -66185.918 | I47: =-MAX(ROUND(Hypotheses!$C$22*I33/Hypotheses!$C$5,0),8)*Hypotheses!$C$23*(1+Hypotheses!$C$24)^6 -> -81739.609
B48: Redevance bail emphyteotique | C48: =-Hypotheses!$C$33 -> -8000 | D48: =-Hypotheses!$C$33 -> -8000 | E48: =-Hypotheses!$C$33 -> -8000 | F48: =-Hypotheses!$C$33 -> -8000 | G48: =-Hypotheses!$C$33 -> -8000 | H48: =-Hypotheses!$C$33 -> -8000 | I48: =-Hypotheses!$C$33 -> -8000
B49: Maintenance, assurance, marketing, admin (% CA) | C49: =-C42*(Hypotheses!$C$27+Hypotheses!$C$28+Hypotheses!$C$29+Hypotheses!$C$30) -> -26165.755 | D49: =-D42*(Hypotheses!$C$27+Hypotheses!$C$28+Hypotheses!$C$29+Hypotheses!$C$30) -> -35412.3 | E49: =-E42*(Hypotheses!$C$27+Hypotheses!$C$28+Hypotheses!$C$29+Hypotheses!$C$30) -> -79530.124 | F49: =-F42*(Hypotheses!$C$27+Hypotheses!$C$28+Hypotheses!$C$29+Hypotheses!$C$30) -> -89238.996 | G49: =-G42*(Hypotheses!$C$27+Hypotheses!$C$28+Hypotheses!$C$29+Hypotheses!$C$30) -> -142583.69 | H49: =-H42*(Hypotheses!$C$27+Hypotheses!$C$28+Hypotheses!$C$29+Hypotheses!$C$30) -> -146420.02 | I49: =-I42*(Hypotheses!$C$27+Hypotheses!$C$28+Hypotheses!$C$29+Hypotheses!$C$30) -> -181074.89
B50: TOTAL CHARGES D'EXPLOITATION | C50: =C46+C47+C48+C49 -> -71432.046 | D50: =D46+D47+D48+D49 -> -85323.852 | E50: =E46+E47+E48+E49 -> -158578.19 | F50: =F46+F47+F48+F49 -> -173640.26 | G50: =G46+G47+G48+G49 -> -269077.72 | H50: =H46+H47+H48+H49 -> -276935.54 | I50: =I46+I47+I48+I49 -> -340476.27
B52: EBITDA | C52: =C44+C50 -> 60144.322 | D52: =D44+D50 -> 92749.428 | E52: =E44+E50 -> 241344.72 | F52: =F44+F50 -> 275104.4 | G52: =G44+G50 -> 447914.56 | H52: =H44+H50 -> 459348 | I52: =I44+I50 -> 570071.77
B54: Amortissements (toutes tranches en service) | C54: =-($C$19-C5*(1+C6))/Hypotheses!$C$37-IF(1>=$D$14,$H$14/Hypotheses!$C$37,0)-IF(1>=$D$15,$H$15/Hypotheses!$C$37,0)-IF(1>=$D$16,$H$16/Hypotheses!$C$37,0) -> -27777.778 | D54: =-($C$19-C5*(1+C6))/Hypotheses!$C$37-IF(2>=$D$14,$H$14/Hypotheses!$C$37,0)-IF(2>=$D$15,$H$15/Hypotheses!$C$37,0)-IF(2>=$D$16,$H$16/Hypotheses!$C$37,0) -> -27777.778 | E54: =-($C$19-C5*(1+C6))/Hypotheses!$C$37-IF(3>=$D$14,$H$14/Hypotheses!$C$37,0)-IF(3>=$D$15,$H$15/Hypotheses!$C$37,0)-IF(3>=$D$16,$H$16/Hypotheses!$C$37,0) -> -64261.111 | F54: =-($C$19-C5*(1+C6))/Hypotheses!$C$37-IF(4>=$D$14,$H$14/Hypotheses!$C$37,0)-IF(4>=$D$15,$H$15/Hypotheses!$C$37,0)-IF(4>=$D$16,$H$16/Hypotheses!$C$37,0) -> -64261.111 | G54: =-($C$19-C5*(1+C6))/Hypotheses!$C$37-IF(5>=$D$14,$H$14/Hypotheses!$C$37,0)-IF(5>=$D$15,$H$15/Hypotheses!$C$37,0)-IF(5>=$D$16,$H$16/Hypotheses!$C$37,0) -> -100744.44 | H54: =-($C$19-C5*(1+C6))/Hypotheses!$C$37-IF(6>=$D$14,$H$14/Hypotheses!$C$37,0)-IF(6>=$D$15,$H$15/Hypotheses!$C$37,0)-IF(6>=$D$16,$H$16/Hypotheses!$C$37,0) -> -100744.44 | I54: =-($C$19-C5*(1+C6))/Hypotheses!$C$37-IF(7>=$D$14,$H$14/Hypotheses!$C$37,0)-IF(7>=$D$15,$H$15/Hypotheses!$C$37,0)-IF(7>=$D$16,$H$16/Hypotheses!$C$37,0) -> -125066.67
B55: EBIT | C55: =C52+C54 -> 32366.544 | D55: =D52+D54 -> 64971.65 | E55: =E52+E54 -> 177083.61 | F55: =F52+F54 -> 210843.29 | G55: =G52+G54 -> 347170.12 | H55: =H52+H54 -> 358603.56 | I55: =I52+I54 -> 445005.11
B56: Charges financieres (interets - emprunt principal + prets tranches) | C56: =-C89 -> -27490.96 | D56: =-D89 -> -48532.236 | E56: =-E89 -> -43159.77 | F56: =-F89 -> -60615.132 | G56: =-G89 -> -51634.071 | H56: =-H89 -> -57794.955 | I56: =-I89 -> -39682.206
B57: RESULTAT AVANT IMPOT (EBT) | C57: =C55+C56 -> 4875.584 | D57: =D55+D56 -> 16439.414 | E57: =E55+E56 -> 133923.84 | F57: =F55+F56 -> 150228.16 | G57: =G55+G56 -> 295536.05 | H57: =H55+H56 -> 300808.6 | I57: =I55+I56 -> 405322.9
A59: 6. IMPOT SUR LES SOCIETES AVEC REPORT DEFICITAIRE (5 ans, CGI Madagascar)
C60: Annee 1 | D60: Annee 2 | E60: Annee 3 | F60: Annee 4 | G60: Annee 5 | H60: Annee 6 | I60: Annee 7
B61: Deficit reportable disponible - debut d'annee | C61: =0 -> 0 | D61: =C65 -> 0 | E61: =D65 -> 0 | F61: =E65 -> 0 | G61: =F65 -> 0 | H61: =G65 -> 0 | I61: =H65 -> 0
B62: Deficit impute sur l'annee | C62: =MIN(MAX(C57,0),C61) -> 0 | D62: =MIN(MAX(D57,0),D61) -> 0 | E62: =MIN(MAX(E57,0),E61) -> 0 | F62: =MIN(MAX(F57,0),F61) -> 0 | G62: =MIN(MAX(G57,0),G61) -> 0 | H62: =MIN(MAX(H57,0),H61) -> 0 | I62: =MIN(MAX(I57,0),I61) -> 0
B63: Base imposable (EBT - deficit impute) | C63: =MAX(C57,0)-C62 -> 4875.584 | D63: =MAX(D57,0)-D62 -> 16439.414 | E63: =MAX(E57,0)-E62 -> 133923.84 | F63: =MAX(F57,0)-F62 -> 150228.16 | G63: =MAX(G57,0)-G62 -> 295536.05 | H63: =MAX(H57,0)-H62 -> 300808.6 | I63: =MAX(I57,0)-I62 -> 405322.9
B64: Impot sur les societes (IS) | C64: =-C63*Hypotheses!$C$36 -> -975.1168 | D64: =-D63*Hypotheses!$C$36 -> -3287.8828 | E64: =-E63*Hypotheses!$C$36 -> -26784.767 | F64: =-F63*Hypotheses!$C$36 -> -30045.632 | G64: =-G63*Hypotheses!$C$36 -> -59107.209 | H64: =-H63*Hypotheses!$C$36 -> -60161.721 | I64: =-I63*Hypotheses!$C$36 -> -81064.58
B65: Deficit reportable - fin d'annee | C65: =MAX(C61-C62,0)+MAX(-C57,0) -> 0 | D65: =MAX(D61-D62,0)+MAX(-D57,0) -> 0 | E65: =MAX(E61-E62,0)+MAX(-E57,0) -> 0 | F65: =MAX(F61-F62,0)+MAX(-F57,0) -> 0 | G65: =MAX(G61-G62,0)+MAX(-G57,0) -> 0 | H65: =MAX(H61-H62,0)+MAX(-H57,0) -> 0 | I65: =MAX(I61-I62,0)+MAX(-I57,0) -> 0
B67: RESULTAT NET (EBT + IS) | C67: =C57+C64 -> 3900.4672 | D67: =D57+D64 -> 13151.531 | E67: =E57+E64 -> 107139.07 | F67: =F57+F64 -> 120182.53 | G67: =G57+G64 -> 236428.84 | H67: =H57+H64 -> 240646.88 | I67: =I57+I64 -> 324258.32
A69: 7. SERVICE DE LA DETTE — EMPRUNT PRINCIPAL + PRETS DEDIES PAR TRANCHE
C70: Annee 1 | D70: Annee 2 | E70: Annee 3 | F70: Annee 4 | G70: Annee 5 | H70: Annee 6 | I70: Annee 7
B71: Annuite emprunt principal (interets + capital, constante) | C71: =IF(0<Hypotheses!$C$43,$C$29*Hypotheses!$C$42/(1-(1+Hypotheses!$C$42)^(-Hypotheses!$C$43)),0) -> 53400.613 | D71: =IF(1<Hypotheses!$C$43,$C$29*Hypotheses!$C$42/(1-(1+Hypotheses!$C$42)^(-Hypotheses!$C$43)),0) -> 53400.613 | E71: =IF(2<Hypotheses!$C$43,$C$29*Hypotheses!$C$42/(1-(1+Hypotheses!$C$42)^(-Hypotheses!$C$43)),0) -> 53400.613 | F71: =IF(3<Hypotheses!$C$43,$C$29*Hypotheses!$C$42/(1-(1+Hypotheses!$C$42)^(-Hypotheses!$C$43)),0) -> 53400.613 | G71: =IF(4<Hypotheses!$C$43,$C$29*Hypotheses!$C$42/(1-(1+Hypotheses!$C$42)^(-Hypotheses!$C$43)),0) -> 53400.613 | H71: =IF(5<Hypotheses!$C$43,$C$29*Hypotheses!$C$42/(1-(1+Hypotheses!$C$42)^(-Hypotheses!$C$43)),0) -> 53400.613 | I71: =IF(6<Hypotheses!$C$43,$C$29*Hypotheses!$C$42/(1-(1+Hypotheses!$C$42)^(-Hypotheses!$C$43)),0) -> 53400.613
B72: Capital restant du emprunt principal - debut periode | C72: =$C$29 -> 366546.13 | D72: =C75 -> 340636.48 | E72: =D75 -> 312783.6 | F72: =E75 -> 282841.76 | G72: =F75 -> 250654.28 | H72: =G75 -> 216052.74 | I72: =H75 -> 178856.08
B73: Interets emprunt principal | C73: =C72*Hypotheses!$C$42 -> 27490.96 | D73: =D72*Hypotheses!$C$42 -> 25547.736 | E73: =E72*Hypotheses!$C$42 -> 23458.77 | F73: =F72*Hypotheses!$C$42 -> 21213.132 | G73: =G72*Hypotheses!$C$42 -> 18799.071 | H73: =H72*Hypotheses!$C$42 -> 16203.955 | I73: =I72*Hypotheses!$C$42 -> 13414.206
B74: Remboursement capital emprunt principal | C74: =C71-C73 -> 25909.653 | D74: =D71-D73 -> 27852.877 | E74: =E71-E73 -> 29941.843 | F74: =F71-F73 -> 32187.481 | G74: =G71-G73 -> 34601.543 | H74: =H71-H73 -> 37196.658 | I74: =I71-I73 -> 39986.408
B75: Capital restant du emprunt principal - fin periode | C75: =MAX(C72-C74,0) -> 340636.48 | D75: =MAX(D72-D74,0) -> 312783.6 | E75: =MAX(E72-E74,0) -> 282841.76 | F75: =MAX(F72-F74,0) -> 250654.28 | G75: =MAX(G72-G74,0) -> 216052.74 | H75: =MAX(H72-H74,0) -> 178856.08 | I75: =MAX(I72-I74,0) -> 138869.67
B77: Pret dedie Tranche 1 - capital restant du debut periode | C77: =IF(OR(1<$D$14-1,1>=$D$14-1+$C$26),0,$H$14*$C$25-(1-$D$14-1)*$H$14*$C$25/$C$26) -> 0 | D77: =IF(OR(2<$D$14-1,2>=$D$14-1+$C$26),0,$H$14*$C$25-(2-$D$14-1)*$H$14*$C$25/$C$26) -> 306460 | E77: =IF(OR(3<$D$14-1,3>=$D$14-1+$C$26),0,$H$14*$C$25-(3-$D$14-1)*$H$14*$C$25/$C$26) -> 262680 | F77: =IF(OR(4<$D$14-1,4>=$D$14-1+$C$26),0,$H$14*$C$25-(4-$D$14-1)*$H$14*$C$25/$C$26) -> 218900 | G77: =IF(OR(5<$D$14-1,5>=$D$14-1+$C$26),0,$H$14*$C$25-(5-$D$14-1)*$H$14*$C$25/$C$26) -> 175120 | H77: =IF(OR(6<$D$14-1,6>=$D$14-1+$C$26),0,$H$14*$C$25-(6-$D$14-1)*$H$14*$C$25/$C$26) -> 131340 | I77: =IF(OR(7<$D$14-1,7>=$D$14-1+$C$26),0,$H$14*$C$25-(7-$D$14-1)*$H$14*$C$25/$C$26) -> 0
B78: Pret dedie Tranche 1 - interets | C78: =C77*Hypotheses!$C$42 -> 0 | D78: =D77*Hypotheses!$C$42 -> 22984.5 | E78: =E77*Hypotheses!$C$42 -> 19701 | F78: =F77*Hypotheses!$C$42 -> 16417.5 | G78: =G77*Hypotheses!$C$42 -> 13134 | H78: =H77*Hypotheses!$C$42 -> 9850.5 | I78: =I77*Hypotheses!$C$42 -> 0
B79: Pret dedie Tranche 1 - remboursement capital | C79: =IF(AND(1>=$D$14-1,1<$D$14-1+$C$26),$H$14*$C$25/$C$26,0) -> 0 | D79: =IF(AND(2>=$D$14-1,2<$D$14-1+$C$26),$H$14*$C$25/$C$26,0) -> 43780 | E79: =IF(AND(3>=$D$14-1,3<$D$14-1+$C$26),$H$14*$C$25/$C$26,0) -> 43780 | F79: =IF(AND(4>=$D$14-1,4<$D$14-1+$C$26),$H$14*$C$25/$C$26,0) -> 43780 | G79: =IF(AND(5>=$D$14-1,5<$D$14-1+$C$26),$H$14*$C$25/$C$26,0) -> 43780 | H79: =IF(AND(6>=$D$14-1,6<$D$14-1+$C$26),$H$14*$C$25/$C$26,0) -> 43780 | I79: =IF(AND(7>=$D$14-1,7<$D$14-1+$C$26),$H$14*$C$25/$C$26,0) -> 0
B81: Pret dedie Tranche 2 - capital restant du debut periode | C81: =IF(OR(1<$D$15-1,1>=$D$15-1+$C$26),0,$H$15*$C$25-(1-$D$15-1)*$H$15*$C$25/$C$26) -> 0 | D81: =IF(OR(2<$D$15-1,2>=$D$15-1+$C$26),0,$H$15*$C$25-(2-$D$15-1)*$H$15*$C$25/$C$26) -> 0 | E81: =IF(OR(3<$D$15-1,3>=$D$15-1+$C$26),0,$H$15*$C$25-(3-$D$15-1)*$H$15*$C$25/$C$26) -> 0 | F81: =IF(OR(4<$D$15-1,4>=$D$15-1+$C$26),0,$H$15*$C$25-(4-$D$15-1)*$H$15*$C$25/$C$26) -> 306460 | G81: =IF(OR(5<$D$15-1,5>=$D$15-1+$C$26),0,$H$15*$C$25-(5-$D$15-1)*$H$15*$C$25/$C$26) -> 262680 | H81: =IF(OR(6<$D$15-1,6>=$D$15-1+$C$26),0,$H$15*$C$25-(6-$D$15-1)*$H$15*$C$25/$C$26) -> 218900 | I81: =IF(OR(7<$D$15-1,7>=$D$15-1+$C$26),0,$H$15*$C$25-(7-$D$15-1)*$H$15*$C$25/$C$26) -> 175120
B82: Pret dedie Tranche 2 - interets | C82: =C81*Hypotheses!$C$42 -> 0 | D82: =D81*Hypotheses!$C$42 -> 0 | E82: =E81*Hypotheses!$C$42 -> 0 | F82: =F81*Hypotheses!$C$42 -> 22984.5 | G82: =G81*Hypotheses!$C$42 -> 19701 | H82: =H81*Hypotheses!$C$42 -> 16417.5 | I82: =I81*Hypotheses!$C$42 -> 13134
B83: Pret dedie Tranche 2 - remboursement capital | C83: =IF(AND(1>=$D$15-1,1<$D$15-1+$C$26),$H$15*$C$25/$C$26,0) -> 0 | D83: =IF(AND(2>=$D$15-1,2<$D$15-1+$C$26),$H$15*$C$25/$C$26,0) -> 0 | E83: =IF(AND(3>=$D$15-1,3<$D$15-1+$C$26),$H$15*$C$25/$C$26,0) -> 0 | F83: =IF(AND(4>=$D$15-1,4<$D$15-1+$C$26),$H$15*$C$25/$C$26,0) -> 43780 | G83: =IF(AND(5>=$D$15-1,5<$D$15-1+$C$26),$H$15*$C$25/$C$26,0) -> 43780 | H83: =IF(AND(6>=$D$15-1,6<$D$15-1+$C$26),$H$15*$C$25/$C$26,0) -> 43780 | I83: =IF(AND(7>=$D$15-1,7<$D$15-1+$C$26),$H$15*$C$25/$C$26,0) -> 43780
B85: Pret dedie Tranche 3 - capital restant du debut periode | C85: =IF(OR(1<$D$16-1,1>=$D$16-1+$C$26),0,$H$16*$C$25-(1-$D$16-1)*$H$16*$C$25/$C$26) -> 0 | D85: =IF(OR(2<$D$16-1,2>=$D$16-1+$C$26),0,$H$16*$C$25-(2-$D$16-1)*$H$16*$C$25/$C$26) -> 0 | E85: =IF(OR(3<$D$16-1,3>=$D$16-1+$C$26),0,$H$16*$C$25-(3-$D$16-1)*$H$16*$C$25/$C$26) -> 0 | F85: =IF(OR(4<$D$16-1,4>=$D$16-1+$C$26),0,$H$16*$C$25-(4-$D$16-1)*$H$16*$C$25/$C$26) -> 0 | G85: =IF(OR(5<$D$16-1,5>=$D$16-1+$C$26),0,$H$16*$C$25-(5-$D$16-1)*$H$16*$C$25/$C$26) -> 0 | H85: =IF(OR(6<$D$16-1,6>=$D$16-1+$C$26),0,$H$16*$C$25-(6-$D$16-1)*$H$16*$C$25/$C$26) -> 204306.67 | I85: =IF(OR(7<$D$16-1,7>=$D$16-1+$C$26),0,$H$16*$C$25-(7-$D$16-1)*$H$16*$C$25/$C$26) -> 175120
B86: Pret dedie Tranche 3 - interets | C86: =C85*Hypotheses!$C$42 -> 0 | D86: =D85*Hypotheses!$C$42 -> 0 | E86: =E85*Hypotheses!$C$42 -> 0 | F86: =F85*Hypotheses!$C$42 -> 0 | G86: =G85*Hypotheses!$C$42 -> 0 | H86: =H85*Hypotheses!$C$42 -> 15323 | I86: =I85*Hypotheses!$C$42 -> 13134
B87: Pret dedie Tranche 3 - remboursement capital | C87: =IF(AND(1>=$D$16-1,1<$D$16-1+$C$26),$H$16*$C$25/$C$26,0) -> 0 | D87: =IF(AND(2>=$D$16-1,2<$D$16-1+$C$26),$H$16*$C$25/$C$26,0) -> 0 | E87: =IF(AND(3>=$D$16-1,3<$D$16-1+$C$26),$H$16*$C$25/$C$26,0) -> 0 | F87: =IF(AND(4>=$D$16-1,4<$D$16-1+$C$26),$H$16*$C$25/$C$26,0) -> 0 | G87: =IF(AND(5>=$D$16-1,5<$D$16-1+$C$26),$H$16*$C$25/$C$26,0) -> 0 | H87: =IF(AND(6>=$D$16-1,6<$D$16-1+$C$26),$H$16*$C$25/$C$26,0) -> 29186.667 | I87: =IF(AND(7>=$D$16-1,7<$D$16-1+$C$26),$H$16*$C$25/$C$26,0) -> 29186.667
B89: TOTAL INTERETS (principal + 3 prets tranches) | C89: =C73+C78+C82+C86 -> 27490.96 | D89: =D73+D78+D82+D86 -> 48532.236 | E89: =E73+E78+E82+E86 -> 43159.77 | F89: =F73+F78+F82+F86 -> 60615.132 | G89: =G73+G78+G82+G86 -> 51634.071 | H89: =H73+H78+H82+H86 -> 57794.955 | I89: =I73+I78+I82+I86 -> 39682.206
B90: TOTAL REMBOURSEMENT CAPITAL (principal + 3 prets tranches) | C90: =C74+C79+C83+C87 -> 25909.653 | D90: =D74+D79+D83+D87 -> 71632.877 | E90: =E74+E79+E83+E87 -> 73721.843 | F90: =F74+F79+F83+F87 -> 119747.48 | G90: =G74+G79+G83+G87 -> 122161.54 | H90: =H74+H79+H83+H87 -> 153943.32 | I90: =I74+I79+I83+I87 -> 112953.07
B92: CASH-FLOW DISPONIBLE POUR L'INVESTISSEUR | C92: =C52+C64-C89-C90-C36 -> 5768.5916 | D92: =D52+D64-D89-D90-D36 -> -359053.57 | E92: =E52+E64-E89-E90-E36 -> 97678.337 | F92: =F52+F64-F89-F90-F36 -> -263653.84 | G92: =G52+G64-G89-G90-G36 -> 215011.74 | H92: =H52+H64-H89-H90-H36 -> -31451.998 | I92: =I52+I64-I89-I90-I36 -> 336371.91
B93: CASH-FLOW CUMULE (avant apport initial) | C93: =-$C$28+C92 -> -674959.94 | D93: =C93+D92 -> -1034013.5 | E93: =D93+E92 -> -936335.17 | F93: =E93+F92 -> -1199989 | G93: =F93+G92 -> -984977.28 | H93: =G93+H92 -> -1016429.3 | I93: =H93+I92 -> -680057.36

Sheet Hypotheses
A1: ECOLODGE SAINTE-MARIE — HYPOTHESES
A2: Toutes les cellules bleues sont modifiables. Montants en EUR sauf indication.
A4: 1. PARAMETRES ETABLISSEMENT
B5: Nombre de chambres | C5: 12
B6: Nuits disponibles / an / chambre | C6: 365
A8: 2. TARIFICATION ET OCCUPATION (montee en charge)
C9: Année 1 | D9: Année 2 | E9: Année 3 | F9: Année 4 | G9: Année 5 | H9: Année 6 | I9: Année 7
B10: Prix moyen chambre / nuit - ADR (EUR) | C10: 190 | D10: 200 | E10: 210 | F10: 216 | G10: 223 | H10: 229 | I10: 236
B11: Taux d'occupation annuel moyen | C11: 0.35 | D11: 0.45 | E11: 0.55 | F11: 0.6 | G11: 0.65 | H11: 0.65 | I11: 0.65
A13: 3. REVENUS ANNEXES (en % du CA Hebergement)
B14: Restauration / bar | C14: 0.38
B15: Spa, bien-etre, excursions, plongee | C15: 0.16
A17: 4. DISTRIBUTION ET CHARGES VARIABLES
B18: Commissions distribution (OTA, agences) en % du CA total | C18: 0.12
B19: Cout matieres restauration en % du CA F&B | C19: 0.32
A21: 5. MASSE SALARIALE
B22: Effectif total (ETP) - ratio ~1,6 ETP/chambre | C22: 19
B23: Cout annuel charge moyen / ETP (EUR) - mix local/encadrement | C23: 3400
B24: Inflation salariale annuelle | C24: 0.04
A26: 6. AUTRES CHARGES D'EXPLOITATION (en % du CA total)
B27: Maintenance, entretien (installations autonomie incluses) | C27: 0.06
B28: Assurances | C28: 0.025
B29: Marketing et communication (hors commissions OTA) | C29: 0.05
B30: Frais administratifs, comptables, juridiques, divers | C30: 0.04
A32: 7. FONCIER
B33: Redevance annuelle bail emphyteotique (EUR) | C33: 8000
A35: 8. FISCALITE
B36: Taux Impot sur les Societes (IS) standard Madagascar | C36: 0.2
B37: Duree amortissement du CAPEX (annees, hors terrain) | C37: 15
A39: 9. FINANCEMENT
B40: Part fonds propres | C40: 0.45
B41: Part emprunt bancaire / dette | C41: =1-C40 -> 0.55
B42: Taux d'interet annuel emprunt | C42: 0.075
B43: Duree emprunt (annees) | C43: 10
B46: Note : ces hypotheses sont des ordres de grandeur de marche pour un ecolodge haut de gamme en ocean Indien, a affiner avec une etude de marche locale (concurrence directe a Sainte-Marie), des devis chantier fermes et un audit RH local avant toute presentation a des financeurs.

Sheet CAPEX
A1: BESOIN D'INVESTISSEMENT (CAPEX)
A2: Montants en EUR. Hypothese : 12 chambres. A confirmer par devis chantier / etudes techniques.
B4: Poste | C4: Montant (EUR) | D4: Base de calcul / commentaire
A5: 1. FONCIER
B6: Droit d'entree bail emphyteotique + frais notaries/EDBM | C6: 40000 | D6: Bail 49-99 ans, hors redevance annuelle (en OPEX)
A8: 2. ETUDES ET AUTORISATIONS
B9: Etudes (architecte, bureau d'etudes, geotechnique) | C9: 35000
B10: Etude d'impact environnemental (EIE) + permis | C10: 18000
B11: Sous-total etudes & autorisations | C11: =SUM(C9:C10) -> 53000
A13: 3. CONSTRUCTION
B14: Gros oeuvre + second oeuvre batiments (EUR/chambre) | C14: 150000 | D14: x nombre de chambres, voir ligne ci-dessous
B15: Construction totale (= cout/chambre x nb chambres) | C15: =C14*Hypotheses!C5 -> 1800000
B16: Espaces communs (restaurant, reception, spa, piscine) | C16: 280000
B17: Amenagements exterieurs, paysager, acces, mobilier ext. | C17: 90000
B18: Sous-total construction | C18: =C15+C16+C17 -> 2170000
A20: 4. AUTONOMIE ENERGIE ET EAU
B21: Centrale photovoltaique + stockage batteries | C21: 130000
B22: Solaire thermique (eau chaude sanitaire) | C22: 20000
B23: Recuperation eaux de pluie + traitement/potabilisation | C23: 45000
B24: Phytoepuration / traitement eaux usees | C24: 35000
B25: Groupe electrogene de secours | C25: 15000
B26: Sous-total autonomie energie & eau | C26: =SUM(C21:C25) -> 245000
A28: 5. EQUIPEMENTS ET MOBILIER (FF&E)
B29: Mobilier, literie, decoration (EUR/chambre) | C29: 12000
B30: FF&E chambres (= EUR/chambre x nb chambres) | C30: =C29*Hypotheses!C5 -> 144000
B31: Cuisine professionnelle et equipement restaurant | C31: 70000
B32: Sous-total FF&E | C32: =C30+C31 -> 214000
A34: 6. FRAIS DE LANCEMENT ET DIVERS
B35: Recrutement, formation equipe, marketing de lancement | C35: 45000
B36: Fonds de roulement initial (stocks, tresorerie demarrage) | C36: 60000
B37: Sous-total lancement | C37: =SUM(C35:C36) -> 105000
B39: SOUS-TOTAL CAPEX (avant imprevus) | C39: =C6+C11+C18+C26+C32+C37 -> 2827000
B40: Imprevus / contingence | C40: 0.1 | D40: % du sous-total ci-dessus, standard chantier insulaire
B41: Montant imprevus | C41: =C39*C40 -> 282700
B43: TOTAL CAPEX | C43: =C39+C41 -> 3109700
B45: dont TOTAL CAPEX amortissable (hors terrain) | C45: =C43-C6 -> 3069700
B46: CAPEX / chambre | C46: =C43/Hypotheses!C5 -> 259141.67

Sheet Compte de resultat
A1: COMPTE DE RESULTAT PREVISIONNEL
A2: Projection 7 ans - Montants en EUR
C4: Annee 1 | D4: Annee 2 | E4: Annee 3 | F4: Annee 4 | G4: Annee 5 | H4: Annee 6 | I4: Annee 7
A5: ACTIVITE
B6: Chambres-nuits vendues | C6: =Hypotheses!$C$5*Hypotheses!$C$6*Hypotheses!C11 -> 1533 | D6: =Hypotheses!$C$5*Hypotheses!$C$6*Hypotheses!D11 -> 1971 | E6: =Hypotheses!$C$5*Hypotheses!$C$6*Hypotheses!E11 -> 2409 | F6: =Hypotheses!$C$5*Hypotheses!$C$6*Hypotheses!F11 -> 2628 | G6: =Hypotheses!$C$5*Hypotheses!$C$6*Hypotheses!G11 -> 2847 | H6: =Hypotheses!$C$5*Hypotheses!$C$6*Hypotheses!H11 -> 2847 | I6: =Hypotheses!$C$5*Hypotheses!$C$6*Hypotheses!I11 -> 2847
B7: Prix moyen chambre - ADR (EUR) | C7: =Hypotheses!C10 -> 190 | D7: =Hypotheses!D10 -> 200 | E7: =Hypotheses!E10 -> 210 | F7: =Hypotheses!F10 -> 216 | G7: =Hypotheses!G10 -> 223 | H7: =Hypotheses!H10 -> 229 | I7: =Hypotheses!I10 -> 236
A8: CHIFFRE D'AFFAIRES
B9: CA Hebergement | C9: =C6*Hypotheses!C10 -> 291270 | D9: =D6*Hypotheses!D10 -> 394200 | E9: =E6*Hypotheses!E10 -> 505890 | F9: =F6*Hypotheses!F10 -> 567648 | G9: =G6*Hypotheses!G10 -> 634881 | H9: =H6*Hypotheses!H10 -> 651963 | I9: =I6*Hypotheses!I10 -> 671892
B10: CA Restauration / bar | C10: =C9*Hypotheses!$C$14 -> 110682.6 | D10: =D9*Hypotheses!$C$14 -> 149796 | E10: =E9*Hypotheses!$C$14 -> 192238.2 | F10: =F9*Hypotheses!$C$14 -> 215706.24 | G10: =G9*Hypotheses!$C$14 -> 241254.78 | H10: =H9*Hypotheses!$C$14 -> 247745.94 | I10: =I9*Hypotheses!$C$14 -> 255318.96
B11: CA Spa / activites / excursions | C11: =C9*Hypotheses!$C$15 -> 46603.2 | D11: =D9*Hypotheses!$C$15 -> 63072 | E11: =E9*Hypotheses!$C$15 -> 80942.4 | F11: =F9*Hypotheses!$C$15 -> 90823.68 | G11: =G9*Hypotheses!$C$15 -> 101580.96 | H11: =H9*Hypotheses!$C$15 -> 104314.08 | I11: =I9*Hypotheses!$C$15 -> 107502.72
B12: CA TOTAL | C12: =C9+C10+C11 -> 448555.8 | D12: =D9+D10+D11 -> 607068 | E12: =E9+E10+E11 -> 779070.6 | F12: =F9+F10+F11 -> 874177.92 | G12: =G9+G10+G11 -> 977716.74 | H12: =H9+H10+H11 -> 1004023 | I12: =I9+I10+I11 -> 1034713.7
B13: Commissions distribution (OTA, agences) | C13: =-C12*Hypotheses!$C$18 -> -53826.696 | D13: =-D12*Hypotheses!$C$18 -> -72848.16 | E13: =-E12*Hypotheses!$C$18 -> -93488.472 | F13: =-F12*Hypotheses!$C$18 -> -104901.35 | G13: =-G12*Hypotheses!$C$18 -> -117326.01 | H13: =-H12*Hypotheses!$C$18 -> -120482.76 | I13: =-I12*Hypotheses!$C$18 -> -124165.64
B14: CA NET | C14: =C12+C13 -> 394729.1 | D14: =D12+D13 -> 534219.84 | E14: =E12+E13 -> 685582.13 | F14: =F12+F13 -> 769276.57 | G14: =G12+G13 -> 860390.73 | H14: =H12+H13 -> 883540.26 | I14: =I12+I13 -> 910548.04
A16: CHARGES D'EXPLOITATION
B17: Cout matieres restauration | C17: =-C10*Hypotheses!$C$19 -> -35418.432 | D17: =-D10*Hypotheses!$C$19 -> -47934.72 | E17: =-E10*Hypotheses!$C$19 -> -61516.224 | F17: =-F10*Hypotheses!$C$19 -> -69025.997 | G17: =-G10*Hypotheses!$C$19 -> -77201.53 | H17: =-H10*Hypotheses!$C$19 -> -79278.701 | I17: =-I10*Hypotheses!$C$19 -> -81702.067
B18: Masse salariale chargee | C18: =-Hypotheses!$C$22*Hypotheses!$C$23*(1+Hypotheses!$C$24)^0 -> -64600 | D18: =-Hypotheses!$C$22*Hypotheses!$C$23*(1+Hypotheses!$C$24)^1 -> -67184 | E18: =-Hypotheses!$C$22*Hypotheses!$C$23*(1+Hypotheses!$C$24)^2 -> -69871.36 | F18: =-Hypotheses!$C$22*Hypotheses!$C$23*(1+Hypotheses!$C$24)^3 -> -72666.214 | G18: =-Hypotheses!$C$22*Hypotheses!$C$23*(1+Hypotheses!$C$24)^4 -> -75572.863 | H18: =-Hypotheses!$C$22*Hypotheses!$C$23*(1+Hypotheses!$C$24)^5 -> -78595.777 | I18: =-Hypotheses!$C$22*Hypotheses!$C$23*(1+Hypotheses!$C$24)^6 -> -81739.609
B19: Redevance bail emphyteotique | C19: =-Hypotheses!$C$33 -> -8000 | D19: =-Hypotheses!$C$33 -> -8000 | E19: =-Hypotheses!$C$33 -> -8000 | F19: =-Hypotheses!$C$33 -> -8000 | G19: =-Hypotheses!$C$33 -> -8000 | H19: =-Hypotheses!$C$33 -> -8000 | I19: =-Hypotheses!$C$33 -> -8000
B20: Maintenance et entretien | C20: =-C12*Hypotheses!$C$27 -> -26913.348 | D20: =-D12*Hypotheses!$C$27 -> -36424.08 | E20: =-E12*Hypotheses!$C$27 -> -46744.236 | F20: =-F12*Hypotheses!$C$27 -> -52450.675 | G20: =-G12*Hypotheses!$C$27 -> -58663.004 | H20: =-H12*Hypotheses!$C$27 -> -60241.381 | I20: =-I12*Hypotheses!$C$27 -> -62082.821
B21: Assurances | C21: =-C12*Hypotheses!$C$28 -> -11213.895 | D21: =-D12*Hypotheses!$C$28 -> -15176.7 | E21: =-E12*Hypotheses!$C$28 -> -19476.765 | F21: =-F12*Hypotheses!$C$28 -> -21854.448 | G21: =-G12*Hypotheses!$C$28 -> -24442.918 | H21: =-H12*Hypotheses!$C$28 -> -25100.575 | I21: =-I12*Hypotheses!$C$28 -> -25867.842
B22: Marketing et communication | C22: =-C12*Hypotheses!$C$29 -> -22427.79 | D22: =-D12*Hypotheses!$C$29 -> -30353.4 | E22: =-E12*Hypotheses!$C$29 -> -38953.53 | F22: =-F12*Hypotheses!$C$29 -> -43708.896 | G22: =-G12*Hypotheses!$C$29 -> -48885.837 | H22: =-H12*Hypotheses!$C$29 -> -50201.151 | I22: =-I12*Hypotheses!$C$29 -> -51735.684
B23: Frais administratifs et divers | C23: =-C12*Hypotheses!$C$30 -> -17942.232 | D23: =-D12*Hypotheses!$C$30 -> -24282.72 | E23: =-E12*Hypotheses!$C$30 -> -31162.824 | F23: =-F12*Hypotheses!$C$30 -> -34967.117 | G23: =-G12*Hypotheses!$C$30 -> -39108.67 | H23: =-H12*Hypotheses!$C$30 -> -40160.921 | I23: =-I12*Hypotheses!$C$30 -> -41388.547
B24: TOTAL CHARGES D'EXPLOITATION | C24: =C17+C18+C19+C20+C21+C22+C23 -> -186515.7 | D24: =D17+D18+D19+D20+D21+D22+D23 -> -229355.62 | E24: =E17+E18+E19+E20+E21+E22+E23 -> -275724.94 | F24: =F17+F18+F19+F20+F21+F22+F23 -> -302673.35 | G24: =G17+G18+G19+G20+G21+G22+G23 -> -331874.82 | H24: =H17+H18+H19+H20+H21+H22+H23 -> -341578.51 | I24: =I17+I18+I19+I20+I21+I22+I23 -> -352516.57
B26: EBITDA (Excedent Brut d'Exploitation) | C26: =C14+C24 -> 208213.41 | D26: =D14+D24 -> 304864.22 | E26: =E14+E24 -> 409857.19 | F26: =F14+F24 -> 466603.22 | G26: =G14+G24 -> 528515.91 | H26: =H14+H24 -> 541961.75 | I26: =I14+I24 -> 558031.47
B27: Marge EBITDA (% CA net) | C27: =C26/C14 -> 0.5274843 | D27: =D26/D14 -> 0.57067184 | E27: =E26/E14 -> 0.59782362 | F27: =F26/F14 -> 0.60654807 | G27: =G26/G14 -> 0.61427429 | H27: =H26/H14 -> 0.61339791 | I27: =I26/I14 -> 0.61285231
A29: RESULTAT
B30: Amortissements (CAPEX hors terrain / duree) | C30: =-CAPEX!$C$45/Hypotheses!$C$37 -> -204646.67 | D30: =-CAPEX!$C$45/Hypotheses!$C$37 -> -204646.67 | E30: =-CAPEX!$C$45/Hypotheses!$C$37 -> -204646.67 | F30: =-CAPEX!$C$45/Hypotheses!$C$37 -> -204646.67 | G30: =-CAPEX!$C$45/Hypotheses!$C$37 -> -204646.67 | H30: =-CAPEX!$C$45/Hypotheses!$C$37 -> -204646.67 | I30: =-CAPEX!$C$45/Hypotheses!$C$37 -> -204646.67
B31: RESULTAT D'EXPLOITATION (EBIT) | C31: =C26+C30 -> 3566.7403 | D31: =D26+D30 -> 100217.55 | E31: =E26+E30 -> 205210.52 | F31: =F26+F30 -> 261956.56 | G31: =G26+G30 -> 323869.24 | H31: =H26+H30 -> 337315.08 | I31: =I26+I30 -> 353384.8
B32: Charges financieres (interets emprunt) | C32: =-Financement!C13 -> -128275.12 | D32: =-Financement!D13 -> -119207.88 | E32: =-Financement!E13 -> -109460.59 | F32: =-Financement!F13 -> -98982.253 | G32: =-Financement!G13 -> -87718.041 | H32: =-Financement!H13 -> -75609.014 | I32: =-Financement!I13 -> -62591.809
B33: RESULTAT AVANT IMPOT | C33: =C31+C32 -> -124708.38 | D33: =D31+D32 -> -18990.325 | E33: =E31+E32 -> 95749.933 | F33: =F31+F32 -> 162974.3 | G33: =G31+G32 -> 236151.2 | H33: =H31+H32 -> 261706.07 | I33: =I31+I32 -> 290792.99
B34: Impot sur les societes (IS) | C34: =-MAX(C33,0)*Hypotheses!$C$36 -> 0 | D34: =-MAX(D33,0)*Hypotheses!$C$36 -> 0 | E34: =-MAX(E33,0)*Hypotheses!$C$36 -> -19149.987 | F34: =-MAX(F33,0)*Hypotheses!$C$36 -> -32594.861 | G34: =-MAX(G33,0)*Hypotheses!$C$36 -> -47230.24 | H34: =-MAX(H33,0)*Hypotheses!$C$36 -> -52341.214 | I34: =-MAX(I33,0)*Hypotheses!$C$36 -> -58158.599
B35: RESULTAT NET | C35: =C33+C34 -> -124708.38 | D35: =D33+D34 -> -18990.325 | E35: =E33+E34 -> 76599.947 | F35: =F33+F34 -> 130379.44 | G35: =G33+G34 -> 188920.96 | H35: =H33+H34 -> 209364.86 | I35: =I33+I34 -> 232634.39

Sheet Financement
A1: PLAN DE FINANCEMENT ET TRESORERIE
A2: Montants en EUR
A4: 1. PLAN DE FINANCEMENT INITIAL
B5: Besoin total en investissement (CAPEX) | C5: =CAPEX!$C$43 -> 3109700
B6: Fonds propres (apport investisseur) | C6: =C5*Hypotheses!$C$40 -> 1399365
B7: Emprunt bancaire / dette | C7: =C5*Hypotheses!$C$41 -> 1710335
B8: TOTAL RESSOURCES | C8: =C6+C7 -> 3109700
A10: 2. TABLEAU D'AMORTISSEMENT DE L'EMPRUNT (annuites constantes)
C11: Annee 1 | D11: Annee 2 | E11: Annee 3 | F11: Annee 4 | G11: Annee 5 | H11: Annee 6 | I11: Annee 7
B12: Capital restant du - debut de periode | C12: =$C$7 -> 1710335 | D12: =C16 -> 1589438.4 | E12: =D16 -> 1459474.5 | F12: =E16 -> 1319763.4 | G12: =F16 -> 1169573.9 | H12: =G16 -> 1008120.2 | I12: =H16 -> 834557.46
B13: Interets de la periode | C13: =C12*Hypotheses!$C$42 -> 128275.12 | D13: =D12*Hypotheses!$C$42 -> 119207.88 | E13: =E12*Hypotheses!$C$42 -> 109460.59 | F13: =F12*Hypotheses!$C$42 -> 98982.253 | G13: =G12*Hypotheses!$C$42 -> 87718.041 | H13: =H12*Hypotheses!$C$42 -> 75609.014 | I13: =I12*Hypotheses!$C$42 -> 62591.809
B14: Annuite (interets + capital) | C14: =IF(0<Hypotheses!$C$43,$C$7*Hypotheses!$C$42/(1-(1+Hypotheses!$C$42)^(-Hypotheses!$C$43)),0) -> 249171.74 | D14: =IF(1<Hypotheses!$C$43,$C$7*Hypotheses!$C$42/(1-(1+Hypotheses!$C$42)^(-Hypotheses!$C$43)),0) -> 249171.74 | E14: =IF(2<Hypotheses!$C$43,$C$7*Hypotheses!$C$42/(1-(1+Hypotheses!$C$42)^(-Hypotheses!$C$43)),0) -> 249171.74 | F14: =IF(3<Hypotheses!$C$43,$C$7*Hypotheses!$C$42/(1-(1+Hypotheses!$C$42)^(-Hypotheses!$C$43)),0) -> 249171.74 | G14: =IF(4<Hypotheses!$C$43,$C$7*Hypotheses!$C$42/(1-(1+Hypotheses!$C$42)^(-Hypotheses!$C$43)),0) -> 249171.74 | H14: =IF(5<Hypotheses!$C$43,$C$7*Hypotheses!$C$42/(1-(1+Hypotheses!$C$42)^(-Hypotheses!$C$43)),0) -> 249171.74 | I14: =IF(6<Hypotheses!$C$43,$C$7*Hypotheses!$C$42/(1-(1+Hypotheses!$C$42)^(-Hypotheses!$C$43)),0) -> 249171.74
B15: Remboursement de capital | C15: =C14-C13 -> 120896.62 | D15: =D14-D13 -> 129963.86 | E15: =E14-E13 -> 139711.15 | F15: =F14-F13 -> 150189.49 | G15: =G14-G13 -> 161453.7 | H15: =H14-H13 -> 173562.73 | I15: =I14-I13 -> 186579.93
B16: Capital restant du - fin de periode | C16: =MAX(C12-C15,0) -> 1589438.4 | D16: =MAX(D12-D15,0) -> 1459474.5 | E16: =MAX(E12-E15,0) -> 1319763.4 | F16: =MAX(F12-F15,0) -> 1169573.9 | G16: =MAX(G12-G15,0) -> 1008120.2 | H16: =MAX(H12-H15,0) -> 834557.46 | I16: =MAX(I12-I15,0) -> 647977.53
A18: 3. FLUX DE TRESORERIE DISPONIBLE POUR L'INVESTISSEUR
C19: Annee 1 | D19: Annee 2 | E19: Annee 3 | F19: Annee 4 | G19: Annee 5 | H19: Annee 6 | I19: Annee 7
B20: EBITDA | C20: ='Compte de resultat'!C26 -> 208213.41 | D20: ='Compte de resultat'!D26 -> 304864.22 | E20: ='Compte de resultat'!E26 -> 409857.19 | F20: ='Compte de resultat'!F26 -> 466603.22 | G20: ='Compte de resultat'!G26 -> 528515.91 | H20: ='Compte de resultat'!H26 -> 541961.75 | I20: ='Compte de resultat'!I26 -> 558031.47
B21: Impot sur les societes | C21: ='Compte de resultat'!C34 -> 0 | D21: ='Compte de resultat'!D34 -> 0 | E21: ='Compte de resultat'!E34 -> -19149.987 | F21: ='Compte de resultat'!F34 -> -32594.861 | G21: ='Compte de resultat'!G34 -> -47230.24 | H21: ='Compte de resultat'!H34 -> -52341.214 | I21: ='Compte de resultat'!I34 -> -58158.599
B22: Interets emprunt | C22: =-C13 -> -128275.12 | D22: =-D13 -> -119207.88 | E22: =-E13 -> -109460.59 | F22: =-F13 -> -98982.253 | G22: =-G13 -> -87718.041 | H22: =-H13 -> -75609.014 | I22: =-I13 -> -62591.809
B23: Remboursement capital emprunt | C23: =-C15 -> -120896.62 | D23: =-D15 -> -129963.86 | E23: =-E15 -> -139711.15 | F23: =-F15 -> -150189.49 | G23: =-G15 -> -161453.7 | H23: =-H15 -> -173562.73 | I23: =-I15 -> -186579.93
B24: CASH-FLOW NET ANNUEL | C24: =C20+C21+C22+C23 -> -40958.334 | D24: =D20+D21+D22+D23 -> 55692.479 | E24: =E20+E21+E22+E23 -> 141535.46 | F24: =F20+F21+F22+F23 -> 184836.62 | G24: =G20+G21+G22+G23 -> 232113.93 | H24: =H20+H21+H22+H23 -> 240448.8 | I24: =I20+I21+I22+I23 -> 250701.13
B25: CASH-FLOW CUMULE (depuis mise en service, avant apport initial) | C25: =-$C$6+C24 -> -1440323.3 | D25: =C25+D24 -> -1384630.9 | E25: =D25+E24 -> -1243095.4 | F25: =E25+F24 -> -1058258.8 | G25: =F25+G24 -> -826144.84 | H25: =G25+H24 -> -585696.05 | I25: =H25+I24 -> -334994.92
